nntecture/__init__.py
nntecture/_base.py
nntecture-1.0.1.dist-info/AUTHORS.rst
nntecture-1.0.1.dist-info/LICENSE
nntecture-1.0.1.dist-info/METADATA
nntecture-1.0.1.dist-info/WHEEL
nntecture-1.0.1.dist-info/top_level.txt
nntecture-1.0.1.dist-info/RECORD
