Metadata-Version: 2.1
Name: nntecture
Version: 1.0.1
Summary: NNtecture is a Python package for Neural Network architecture visualization.
Home-page: https://github.com/kristianbonnici/nntecture
Author: Kristian Bonnici
Author-email: kristiandaaniel@gmail.com
License: MIT license
Keywords: nntecture
Platform: UNKNOWN
Classifier: Development Status :: 5 - Production/Stable
Classifier: Intended Audience :: Developers
Classifier: License :: OSI Approved :: MIT License
Classifier: Natural Language :: English
Classifier: Programming Language :: Python :: 3
Classifier: Programming Language :: Python :: 3.6
Classifier: Programming Language :: Python :: 3.7
Classifier: Programming Language :: Python :: 3.8
Classifier: Programming Language :: Python :: 3.9
Classifier: Programming Language :: Python :: 3.10
Requires-Python: >=3.6
Requires-Dist: pytest
Requires-Dist: setuptools
Requires-Dist: graphviz
